arq_prometheus/__init__.py
arq_prometheus/client.py
arq_prometheus-0.3.0.dist-info/LICENSE
arq_prometheus-0.3.0.dist-info/METADATA
arq_prometheus-0.3.0.dist-info/WHEEL
arq_prometheus-0.3.0.dist-info/RECORD
