Metadata-Version: 2.1
Name: arq-prometheus
Version: 0.3.0
Summary: Prometheus metrics for arq job queues
Keywords: arq,prometheus,metrics
Author: Santiago Fraire Willemoes
Author-email: santiago.fraire@kpn.com
Requires-Python: >=3.8,<4.0
Classifier: Intended Audience :: Developers
Classifier: Programming Language :: Python :: 3
Classifier: Programming Language :: Python :: 3.8
Classifier: Programming Language :: Python :: 3.9
Classifier: Programming Language :: Python :: 3.10
Classifier: Programming Language :: Python :: 3.11
Classifier: Programming Language :: Python :: 3.8
Classifier: Programming Language :: Python :: 3.9
Classifier: Programming Language :: Python :: Implementation :: CPython
Classifier: Topic :: Software Development :: Libraries :: Application Frameworks
Requires-Dist: arq (>0.23,<1.0)
Requires-Dist: prometheus-client (>=0.14.1,<1.0.0)
